<?xml version="1.0" encoding="UTF-8"?>
<!DOCTYPE pdf2xml SYSTEM "pdf2xml.dtd">

<pdf2xml producer="poppler" version="0.24.5">
<page number="1" position="absolute" top="0" left="0" height="1188" width="918">
	<fontspec id="0" size="28" family="Times" color="#000000"/>
	<fontspec id="1" size="12" family="Times" color="#000000"/>
	<fontspec id="2" size="13" family="Symbol" color="#000000"/>
	<fontspec id="3" size="13" family="Times" color="#000000"/>
	<fontspec id="4" size="14" family="Times" color="#000000"/>
	<fontspec id="5" size="14" family="Times" color="#000000"/>
	<fontspec id="6" size="14" family="Times" color="#000000"/>
	<fontspec id="7" size="14" family="Symbol" color="#000000"/>
	<fontspec id="8" size="12" family="Times" color="#212121"/>
	<fontspec id="9" size="12" family="Symbol" color="#212121"/>
	<fontspec id="10" size="14" family="Times" color="#000000"/>
<text top="61" left="348" width="230" height="27" font="0"><b>Maria Baldonieri </b></text>
<text top="94" left="41" width="104" height="13" font="1">5 Chestnut Road </text>
<text top="88" left="144" width="11" height="19" font="2"></text>
<text top="94" left="156" width="558" height="13" font="1">Bradford Woods, PA 15015                                                            318 W Nittany Ave APT 1 </text>
<text top="88" left="714" width="7" height="19" font="2"></text>
<text top="94" left="721" width="156" height="13" font="1">  State College, PA 16801</text>
<text top="90" left="877" width="4" height="19" font="3"> </text>
<text top="113" left="338" width="138" height="13" font="1">mgb5190@gmail.com </text>
<text top="108" left="476" width="7" height="19" font="2"></text>
<text top="113" left="483" width="101" height="13" font="1"> (724) 799-6332 </text>
<text top="130" left="39" width="4" height="13" font="1"> </text>
<text top="148" left="39" width="111" height="15" font="4"><b>EDUCATION: </b></text>
<text top="144" left="336" width="4" height="15" font="5"> </text>
<text top="144" left="709" width="4" height="15" font="5"> </text>
<text top="167" left="39" width="247" height="15" font="4"><b>The Pennsylvania State University </b></text>
<text top="167" left="336" width="4" height="15" font="4"><b> </b></text>
<text top="167" left="736" width="147" height="15" font="4"><b>University Park, PA </b></text>
<text top="186" left="39" width="158" height="15" font="6"><i>College of Engineering </i></text>
<text top="186" left="336" width="4" height="15" font="6"><i> </i></text>
<text top="186" left="756" width="127" height="15" font="4"><b>Major GPA: </b>3.38 </text>
<text top="205" left="39" width="176" height="15" font="5">B.S.  in Civil Engineering </text>
<text top="205" left="336" width="4" height="15" font="5"> </text>
<text top="205" left="716" width="166" height="15" font="6"><i>Graduation Spring 2016</i><b> </b></text>
<text top="230" left="39" width="122" height="15" font="4"><b>EXPERIENCE:  </b></text>
<text top="225" left="336" width="4" height="15" font="5"> </text>
<text top="225" left="879" width="4" height="15" font="5"> </text>
<text top="249" left="39" width="351" height="15" font="4"><b>The Pennsylvania State University Physical Plant</b> </text>
<text top="268" left="39" width="187" height="15" font="6"><i>Project Management Intern </i></text>
<text top="249" left="736" width="147" height="15" font="4"><b>University Park, PA </b></text>
<text top="268" left="846" width="37" height="15" font="6"><i>2015 </i></text>
<text top="282" left="66" width="8" height="20" font="7"></text>
<text top="287" left="74" width="594" height="15" font="5">  Assists in the project management of University engineering and construction projects </text>
<text top="307" left="120" width="10" height="15" font="5">- </text>
<text top="307" left="147" width="344" height="15" font="5">Leading a project on renovations in Beaver Stadium</text>
<text top="308" left="492" width="4" height="13" font="8"> </text>
<text top="326" left="120" width="10" height="15" font="5">- </text>
<text top="326" left="147" width="626" height="15" font="5">Acting as point of contact for three concurrent projects in Beaver Stadium and Schreyer House</text>
<text top="327" left="773" width="4" height="13" font="8"> </text>
<text top="341" left="66" width="7" height="18" font="9"></text>
<text top="345" left="73" width="4" height="14" font="8"> </text>
<text top="345" left="93" width="367" height="15" font="5">Provide input to populate project management database</text>
<text top="346" left="460" width="4" height="13" font="8"> </text>
<text top="364" left="120" width="10" height="15" font="5">- </text>
<text top="364" left="147" width="581" height="15" font="5">Accounts for all contracts and funding requests submitted for approximately 40 projects</text>
<text top="365" left="728" width="4" height="13" font="8"> </text>
<text top="383" left="120" width="10" height="15" font="5">- </text>
<text top="383" left="147" width="467" height="15" font="5">Creates documents to keep track of financial statuses of active projects</text>
<text top="384" left="615" width="4" height="13" font="8"> </text>
<text top="398" left="66" width="7" height="18" font="9"></text>
<text top="402" left="73" width="4" height="14" font="8"> </text>
<text top="402" left="93" width="176" height="15" font="5">Organized Intern activities</text>
<text top="403" left="269" width="4" height="13" font="8"> </text>
<text top="421" left="120" width="10" height="15" font="5">- </text>
<text top="421" left="147" width="246" height="15" font="5">Arranged Intern/Supervisor Liaisons </text>
<text top="440" left="120" width="10" height="15" font="5">- </text>
<text top="440" left="147" width="375" height="15" font="5">Coordinated active project tours throughout the summer </text>
<text top="461" left="39" width="138" height="15" font="4"><b>Hatch Engineering </b></text>
<text top="480" left="39" width="176" height="15" font="6"><i>Assistant Buyer/Expediter </i></text>
<text top="461" left="773" width="110" height="15" font="4"><b>Pittsburgh, PA </b></text>
<text top="480" left="846" width="37" height="15" font="6"><i>2014 </i></text>
<text top="496" left="69" width="7" height="18" font="9"></text>
<text top="501" left="76" width="4" height="14" font="8"> </text>
<text top="500" left="96" width="210" height="15" font="5">Facilitated supplier bid process:</text>
<text top="501" left="306" width="4" height="13" font="8"> </text>
<text top="519" left="120" width="10" height="15" font="5">- </text>
<text top="519" left="147" width="373" height="15" font="5">Established qualified bidders list from existing data base</text>
<text top="520" left="521" width="4" height="13" font="8"> </text>
<text top="538" left="120" width="10" height="15" font="5">- </text>
<text top="538" left="147" width="594" height="15" font="5">Acted as point of contact between Hatch supply chain and Bidders throughout bid process</text>
<text top="539" left="742" width="4" height="13" font="8"> </text>
<text top="557" left="120" width="10" height="15" font="5">- </text>
<text top="557" left="147" width="457" height="15" font="5">Coordinated correspondence between Hatch Engineering and bidders</text>
<text top="558" left="605" width="4" height="13" font="8"> </text>
<text top="576" left="120" width="10" height="15" font="5">- </text>
<text top="576" left="147" width="197" height="15" font="5">Generated bid evaluation tabs</text>
<text top="577" left="344" width="4" height="13" font="8"> </text>
<text top="591" left="69" width="7" height="18" font="9"></text>
<text top="596" left="76" width="4" height="14" font="8"> </text>
<text top="595" left="96" width="196" height="15" font="5">Assisted in supplier oversight</text>
<text top="596" left="291" width="4" height="13" font="8"> </text>
<text top="614" left="120" width="10" height="15" font="5">- </text>
<text top="614" left="147" width="336" height="15" font="5">Expedited supplier submittal of technical packages</text>
<text top="615" left="483" width="4" height="13" font="8"> </text>
<text top="633" left="120" width="10" height="15" font="5">- </text>
<text top="633" left="147" width="504" height="15" font="5">Coordinated internal data distribution and technical review with engineering</text>
<text top="634" left="652" width="4" height="13" font="8"> </text>
<text top="652" left="120" width="10" height="15" font="5">- </text>
<text top="652" left="147" width="314" height="15" font="5">Expedited Quality Management data submittals</text>
<text top="653" left="462" width="4" height="13" font="8"> </text>
<text top="671" left="120" width="10" height="15" font="5">- </text>
<text top="671" left="147" width="364" height="15" font="5">Verified completion of supplier submittal requirements</text>
<text top="672" left="512" width="4" height="13" font="8"> </text>
<text top="686" left="69" width="8" height="20" font="7"></text>
<text top="690" left="76" width="275" height="15" font="5">  Set up Project document filing system </text>
<text top="716" left="39" width="227" height="15" font="4"><b>LEADERSHIP / ACTIVITIES: </b></text>
<text top="711" left="360" width="4" height="15" font="5"> </text>
<text top="711" left="879" width="4" height="15" font="5"> </text>
<text top="739" left="39" width="223" height="15" font="4"><b>Special Olympics Pennsylvania </b></text>
<text top="734" left="360" width="4" height="15" font="5"> </text>
<text top="735" left="756" width="127" height="15" font="4"><b>State College, PA </b></text>
<text top="754" left="66" width="8" height="20" font="7"></text>
<text top="758" left="74" width="472" height="15" font="5">  Aided in the set-up and tear down of ceremonies and athletic events </text>
<text top="758" left="846" width="37" height="15" font="6"><i>2015 </i></text>
<text top="778" left="39" width="267" height="15" font="4"><b>Penn State Dance Marathon (THON) </b></text>
<text top="778" left="360" width="4" height="15" font="4"><b> </b></text>
<text top="778" left="736" width="147" height="15" font="4"><b>University Park, PA </b></text>
<text top="798" left="39" width="191" height="15" font="10"><i><b>AYUDA Benefitting THON </b></i></text>
<text top="797" left="360" width="4" height="15" font="6"><i> </i></text>
<text top="797" left="783" width="100" height="15" font="6"><i> 2012- present </i></text>
<text top="817" left="39" width="101" height="15" font="6"><i>Vice President </i></text>
<text top="817" left="360" width="4" height="15" font="6"><i> </i></text>
<text top="817" left="879" width="4" height="15" font="6"><i> </i></text>
<text top="832" left="66" width="8" height="20" font="7"></text>
<text top="837" left="74" width="436" height="15" font="5">  Present important information during meetings to 35 members </text>
<text top="853" left="66" width="8" height="20" font="7"></text>
<text top="857" left="74" width="316" height="15" font="5">  Organize bonding activities for organization<i> </i></text>
<text top="873" left="66" width="8" height="20" font="7"></text>
<text top="877" left="74" width="514" height="15" font="5">  Submit bi-weekly reports for fundraising, family relations and recruitment<i> </i></text>
<text top="893" left="66" width="8" height="20" font="7"></text>
<text top="898" left="74" width="443" height="15" font="5">  Record and publish all meeting minutes to online filing system<i>  </i></text>
<text top="917" left="39" width="128" height="15" font="6"><i>Fundraising Chair </i></text>
<text top="917" left="360" width="4" height="15" font="6"><i> </i></text>
<text top="917" left="879" width="4" height="15" font="6"><i> </i></text>
<text top="933" left="66" width="8" height="20" font="7"></text>
<text top="937" left="74" width="635" height="15" font="5">  Led the planning of all 10 fundraising events for the organization throughout the school year </text>
<text top="953" left="66" width="8" height="20" font="7"></text>
<text top="958" left="74" width="383" height="15" font="5">  Ensured the money raised was properly accounted for  </text>
<text top="973" left="66" width="8" height="20" font="7"></text>
<text top="978" left="74" width="560" height="15" font="5">  Completed and submitted all necessary paper work and reports in a timely manor </text>
<text top="997" left="39" width="240" height="15" font="6"><i>Special Projects/Recruitment Chair </i></text>
<text top="997" left="360" width="4" height="15" font="6"><i> </i></text>
<text top="997" left="879" width="4" height="15" font="6"><i> </i></text>
<text top="1013" left="66" width="8" height="20" font="7"></text>
<text top="1017" left="74" width="339" height="15" font="5">  Orchestrated recruitment events around campus<i><b> </b></i></text>
<text top="1033" left="66" width="8" height="20" font="7"></text>
<text top="1037" left="74" width="5" height="15" font="5"> </text>
<text top="1035" left="93" width="392" height="18" font="5">Maintained the organization’s website and social networks<i><b> </b></i></text>
<text top="1063" left="39" width="69" height="15" font="4"><b>SKILLS: </b></text>
<text top="1058" left="336" width="4" height="15" font="5"> </text>
<text top="1058" left="879" width="4" height="15" font="5"> </text>
<text top="1082" left="93" width="537" height="15" font="5">SolidWorks              Microsoft Office Suite              AutoCAD              SAP2000 </text>
<text top="1101" left="76" width="4" height="15" font="5"> </text>
</page>
</pdf2xml>
