<?xml version="1.0" encoding="UTF-8"?>
<!DOCTYPE pdf2xml SYSTEM "pdf2xml.dtd">

<pdf2xml producer="poppler" version="0.24.5">
<page number="1" position="absolute" top="0" left="0" height="1188" width="918">
	<fontspec id="0" size="68" family="Times" color="#000000"/>
	<fontspec id="1" size="91" family="Times" color="#000000"/>
	<fontspec id="2" size="27" family="Times" color="#000000"/>
	<fontspec id="3" size="21" family="Times" color="#000000"/>
	<fontspec id="4" size="15" family="Times" color="#000000"/>
	<fontspec id="5" size="24" family="Times" color="#000000"/>
	<fontspec id="6" size="44" family="Times" color="#000000"/>
	<fontspec id="7" size="15" family="Times" color="#5c34ff"/>
	<fontspec id="8" size="15" family="Times" color="#000000"/>
	<fontspec id="9" size="21" family="Times" color="#000000"/>
	<fontspec id="10" size="15" family="Times" color="#e32400"/>
<text top="132" left="226" width="466" height="86" font="0">Jihoon Chris Lee</text>
<text top="109" left="692" width="17" height="115" font="1"> </text>
<text top="230" left="258" width="401" height="29" font="2">Graphic Designer &amp; UX Designer</text>
<text top="263" left="296" width="333" height="23" font="3">“I am a designer I am an artist.” </text>
<text top="307" left="311" width="296" height="18" font="4">jcl0417@gmail.com   |   201.281.7841</text>
<text top="328" left="319" width="280" height="18" font="4">http://jclgraphicart.carbonmade.com</text>
<text top="371" left="395" width="128" height="26" font="5"><b>Education</b></text>
<text top="355" left="523" width="13" height="47" font="6"><b> </b></text>
<text top="406" left="203" width="175" height="18" font="7"><b>New York University </b></text>
<text top="426" left="153" width="270" height="18" font="8"><b>Digital Art / Graphic Design BFA</b></text>
<text top="453" left="232" width="113" height="18" font="8"><b>Class of 2014</b></text>
<text top="448" left="344" width="7" height="23" font="9"><b> </b></text>
<text top="409" left="555" width="66" height="18" font="10"><b>General</b></text>
<text top="409" left="620" width="88" height="18" font="8"><b> Assembly</b></text>
<text top="430" left="562" width="140" height="18" font="8"><b>Certificate Letter</b></text>
<text top="451" left="612" width="39" height="18" font="8"><b>2015</b></text>
<text top="480" left="115" width="75" height="26" font="5"><b>Profile</b></text>
<text top="511" left="140" width="6" height="18" font="8"><b>•</b></text>
<text top="513" left="177" width="273" height="16" font="4">︎︎Meticulous with design &amp; creativity </text>
<text top="533" left="140" width="6" height="18" font="4">•</text>
<text top="535" left="177" width="245" height="16" font="4">︎︎Always try be a problem solver </text>
<text top="555" left="140" width="6" height="18" font="4">•</text>
<text top="557" left="177" width="211" height="16" font="4">︎︎Good multi-tasker &amp; under </text>
<text top="577" left="177" width="73" height="18" font="4">pressure </text>
<text top="597" left="140" width="6" height="18" font="4">•</text>
<text top="597" left="177" width="214" height="18" font="4">Fluent in Korean &amp; English </text>
<text top="618" left="140" width="6" height="18" font="4">•</text>
<text top="618" left="177" width="236" height="18" font="4">Quick learner &amp; willingness to </text>
<text top="639" left="177" width="44" height="18" font="4">learn </text>
<text top="659" left="140" width="6" height="18" font="4">•</text>
<text top="661" left="177" width="259" height="16" font="4">︎Energetic with passion for design</text>
<text top="681" left="140" width="6" height="18" font="4">•</text>
<text top="683" left="177" width="244" height="16" font="4">︎Have strong visualization skills </text>
<text top="545" left="484" width="6" height="18" font="4">•</text>
<text top="546" left="521" width="188" height="16" font="4">︎︎Great sense with Colors</text>
<text top="567" left="484" width="6" height="18" font="4">•</text>
<text top="567" left="521" width="151" height="18" font="4">Creating User Flow</text>
<text top="587" left="484" width="6" height="18" font="4">•</text>
<text top="587" left="521" width="107" height="18" font="4">Visual Design</text>
<text top="608" left="484" width="6" height="18" font="4">•</text>
<text top="608" left="521" width="79" height="18" font="4">Personas </text>
<text top="628" left="484" width="6" height="18" font="4">•</text>
<text top="628" left="521" width="175" height="18" font="4">Wireframe Prototyping</text>
<text top="649" left="484" width="6" height="18" font="4">•</text>
<text top="649" left="521" width="142" height="18" font="4">Interaction Design</text>
<text top="746" left="115" width="167" height="26" font="5"><b>Personal Skills</b></text>
<text top="788" left="140" width="6" height="18" font="4">•</text>
<text top="788" left="177" width="100" height="18" font="4">Photography</text>
<text top="788" left="369" width="6" height="18" font="4">•</text>
<text top="788" left="406" width="156" height="18" font="4">Strong Visualization</text>
<text top="777" left="599" width="6" height="18" font="4">•</text>
<text top="777" left="635" width="152" height="18" font="4">Well rounded SMS </text>
<text top="798" left="635" width="86" height="18" font="4">experience</text>
<text top="820" left="140" width="6" height="18" font="4">•</text>
<text top="820" left="177" width="120" height="18" font="4">Handy with my </text>
<text top="840" left="177" width="48" height="18" font="4">hands</text>
<text top="820" left="369" width="6" height="18" font="4">•</text>
<text top="820" left="406" width="144" height="18" font="4">Strong &amp; Creative </text>
<text top="840" left="406" width="93" height="18" font="4">Typography</text>
<text top="820" left="599" width="6" height="18" font="4">•</text>
<text top="820" left="635" width="112" height="18" font="4">Experience in </text>
<text top="840" left="635" width="113" height="18" font="4">Printing Media</text>
<text top="916" left="115" width="62" height="26" font="5"><b>Skills</b></text>
<text top="949" left="140" width="6" height="18" font="4">•</text>
<text top="948" left="177" width="84" height="18" font="4">Photoshop</text>
<text top="948" left="369" width="6" height="18" font="4">•</text>
<text top="948" left="406" width="89" height="18" font="4">HTML/CSS</text>
<text top="948" left="599" width="6" height="18" font="4">•</text>
<text top="948" left="635" width="141" height="18" font="4">Processing (Java)</text>
<text top="972" left="140" width="6" height="18" font="4">•</text>
<text top="972" left="177" width="72" height="18" font="4">Illustrator</text>
<text top="972" left="369" width="6" height="18" font="4">•</text>
<text top="972" left="406" width="118" height="18" font="4">Dream Weaver</text>
<text top="972" left="599" width="6" height="18" font="4">•</text>
<text top="972" left="635" width="118" height="18" font="4">Microsoft Word</text>
<text top="995" left="140" width="6" height="18" font="4">•</text>
<text top="995" left="177" width="70" height="18" font="4">InDesign</text>
<text top="995" left="369" width="6" height="18" font="4">•</text>
<text top="995" left="406" width="104" height="18" font="4">Premiere Pro</text>
<text top="995" left="599" width="6" height="18" font="4">•</text>
<text top="995" left="635" width="43" height="18" font="4">Excel</text>
<text top="1019" left="140" width="6" height="18" font="4">•</text>
<text top="1019" left="177" width="96" height="18" font="4">After Effects</text>
<text top="1019" left="369" width="6" height="18" font="4">•</text>
<text top="1019" left="406" width="70" height="18" font="4">Final Cut</text>
<text top="1019" left="599" width="6" height="18" font="4">•</text>
<text top="1019" left="635" width="95" height="18" font="4">Power Point</text>
</page>
<page number="2" position="absolute" top="0" left="0" height="1188" width="918">
<text top="3" left="140" width="6" height="18" font="4">•</text>
<text top="3" left="177" width="84" height="18" font="4">Photoshop</text>
<text top="3" left="369" width="6" height="18" font="4">•</text>
<text top="3" left="406" width="89" height="18" font="4">HTML/CSS</text>
<text top="3" left="599" width="6" height="18" font="4">•</text>
<text top="3" left="635" width="141" height="18" font="4">Processing (Java)</text>
<text top="26" left="140" width="6" height="18" font="4">•</text>
<text top="26" left="177" width="72" height="18" font="4">Illustrator</text>
<text top="26" left="369" width="6" height="18" font="4">•</text>
<text top="26" left="406" width="118" height="18" font="4">Dream Weaver</text>
<text top="26" left="599" width="6" height="18" font="4">•</text>
<text top="26" left="635" width="118" height="18" font="4">Microsoft Word</text>
<text top="50" left="140" width="6" height="18" font="4">•</text>
<text top="50" left="177" width="70" height="18" font="4">InDesign</text>
<text top="50" left="369" width="6" height="18" font="4">•</text>
<text top="50" left="406" width="104" height="18" font="4">Premiere Pro</text>
<text top="50" left="599" width="6" height="18" font="4">•</text>
<text top="50" left="635" width="43" height="18" font="4">Excel</text>
<text top="73" left="140" width="6" height="18" font="4">•</text>
<text top="73" left="177" width="96" height="18" font="4">After Effects</text>
<text top="73" left="369" width="6" height="18" font="4">•</text>
<text top="73" left="406" width="70" height="18" font="4">Final Cut</text>
<text top="73" left="599" width="6" height="18" font="4">•</text>
<text top="73" left="635" width="95" height="18" font="4">Power Point</text>
<text top="153" left="115" width="126" height="26" font="5"><b>Experience</b></text>
<text top="180" left="115" width="334" height="31" font="5"><b>Descendent of Thieves</b></text>
<text top="213" left="115" width="147" height="18" font="4">11.3.2014~Current</text>
<text top="234" left="115" width="278" height="18" font="4">Web Designer/UX Designer (Intern)</text>
<text top="255" left="115" width="616" height="18" font="4">Objectives: Redesigned the entire website &amp; created wireframe for the website.</text>
<text top="275" left="131" width="6" height="18" font="4">•</text>
<text top="275" left="168" width="96" height="18" font="4">Web Design</text>
<text top="296" left="131" width="6" height="18" font="4">•</text>
<text top="296" left="168" width="243" height="18" font="4">User Experience Visual Design</text>
<text top="316" left="131" width="6" height="18" font="4">•</text>
<text top="316" left="168" width="277" height="18" font="4">User Experience Interaction Design</text>
<text top="355" left="115" width="255" height="31" font="5"><b>Fesco/Chargeworx</b></text>
<text top="388" left="115" width="157" height="18" font="4">8.5.2014~8.29.2014</text>
<text top="409" left="115" width="232" height="18" font="4">Graphic Designer (Freelance)</text>
<text top="429" left="115" width="404" height="18" font="4">Objectives: Package Design, Poster, Flyer Designs.</text>
<text top="450" left="131" width="6" height="18" font="4">•</text>
<text top="450" left="168" width="143" height="18" font="4">Package dyelining</text>
<text top="470" left="131" width="6" height="18" font="4">•</text>
<text top="470" left="168" width="184" height="18" font="4">Advertise poster design</text>
<text top="491" left="131" width="6" height="18" font="4">•</text>
<text top="491" left="168" width="140" height="18" font="4">Catalogue Design</text>
<text top="530" left="115" width="350" height="31" font="5"><b>NYU Senior Thesis Show</b></text>
<text top="563" left="115" width="167" height="18" font="4">3.12.2014~3.19.2014</text>
<text top="583" left="115" width="107" height="18" font="4">Graphic Artist</text>
<text top="604" left="115" width="682" height="18" font="4">Objectives: Displayed several pieces and coordinated the show. Created the Exhibition </text>
<text top="625" left="115" width="38" height="18" font="4">flyer.</text>
<text top="645" left="131" width="6" height="18" font="4">•</text>
<text top="645" left="168" width="180" height="18" font="4">Exhibition Flyer Design</text>
<text top="666" left="131" width="6" height="18" font="4">•</text>
<text top="666" left="168" width="173" height="18" font="4">Exhibition Coordinator</text>
<text top="686" left="131" width="6" height="18" font="4">•</text>
<text top="686" left="168" width="120" height="18" font="4">Exhibition artist</text>
<text top="725" left="115" width="159" height="31" font="5"><b>Rhingo USA</b></text>
<text top="758" left="115" width="111" height="18" font="4">Summer 2013</text>
<text top="779" left="115" width="137" height="18" font="4">Graphic Designer</text>
<text top="799" left="115" width="616" height="18" font="4">Objectives: Logo, Banner, T-shirt, Stickers, &amp; Chacacter Designs. (Print based)</text>
<text top="820" left="131" width="6" height="18" font="4">•</text>
<text top="820" left="168" width="101" height="18" font="4">Shirt Printing</text>
<text top="840" left="131" width="6" height="18" font="4">•</text>
<text top="840" left="168" width="117" height="18" font="4">Banner Design</text>
<text top="861" left="131" width="6" height="18" font="4">•</text>
<text top="861" left="168" width="212" height="18" font="4">Poster, logo, sticker design</text>
<text top="879" left="115" width="223" height="31" font="5"><b>Campus Clipper</b></text>
<text top="912" left="115" width="118" height="18" font="4">3.2012~8.2012</text>
<text top="933" left="115" width="183" height="18" font="4">Graphic Design (Intern)</text>
<text top="954" left="115" width="623" height="18" font="4">Objectives: Coupon &amp; Magazine cover design, SMS Advertising w/ Facebook &amp; </text>
<text top="974" left="115" width="74" height="18" font="4">Pinterest.</text>
<text top="995" left="131" width="6" height="18" font="4">•</text>
<text top="995" left="168" width="130" height="18" font="4">SMS Advertising</text>
<text top="1015" left="131" width="6" height="18" font="4">•</text>
<text top="1015" left="168" width="188" height="18" font="4">Magazine Cover Design</text>
<text top="1036" left="131" width="6" height="18" font="4">•</text>
<text top="1036" left="168" width="121" height="18" font="4">Coupon Design</text>
</page>
<page number="3" position="absolute" top="0" left="0" height="1188" width="918">
<text top="108" left="115" width="286" height="31" font="5"><b>Cooper Art Academy</b></text>
<text top="141" left="115" width="128" height="18" font="4">1.2008~11.2009</text>
<text top="162" left="115" width="156" height="18" font="4">School Manager/TA</text>
<text top="183" left="115" width="526" height="18" font="4">Objectives: Help students prepare portfolio for College applications.</text>
</page>
</pdf2xml>
