<?xml version="1.0" encoding="UTF-8"?>
<!DOCTYPE pdf2xml SYSTEM "pdf2xml.dtd">

<pdf2xml producer="poppler" version="0.24.5">
<page number="1" position="absolute" top="0" left="0" height="1188" width="918">
	<fontspec id="0" size="34" family="Times" color="#344876"/>
	<fontspec id="1" size="16" family="Times" color="#000000"/>
	<fontspec id="2" size="14" family="Times" color="#000000"/>
	<fontspec id="3" size="14" family="Times" color="#344876"/>
	<fontspec id="4" size="14" family="Times" color="#4d4d4d"/>
	<fontspec id="5" size="14" family="Times" color="#4d4d4d"/>
	<fontspec id="6" size="14" family="Times" color="#da241a"/>
	<fontspec id="7" size="15" family="Symbol" color="#000000"/>
	<fontspec id="8" size="15" family="Times" color="#000000"/>
	<fontspec id="9" size="13" family="Times" color="#000000"/>
<text top="54" left="310" width="299" height="47" font="0">Raghen N. Morrow</text>
<text top="118" left="108" width="122" height="20" font="1">315 Shady Dirve</text>
<text top="118" left="230" width="13" height="20" font="2">⎮ </text>
<text top="118" left="243" width="142" height="20" font="1">Crescent, PA 15046</text>
<text top="118" left="385" width="278" height="20" font="2">⎮ (412) 874­9758 ⎮ raghenm@gmail.com</text>
<text top="175" left="124" width="4" height="21" font="3"> </text>
<text top="176" left="108" width="15" height="20" font="3">➤</text>
<text top="175" left="128" width="101" height="21" font="3">OBJECTIVE:</text>
<text top="211" left="162" width="614" height="20" font="4">To be awarded a position that will utilize my experience with research, project management, </text>
<text top="231" left="108" width="192" height="20" font="4">multi­tasking and leadership.</text>
<text top="301" left="124" width="4" height="21" font="3"> </text>
<text top="302" left="108" width="15" height="20" font="3">➤</text>
<text top="301" left="128" width="106" height="21" font="3">EDUCATION:</text>
<text top="338" left="108" width="362" height="21" font="4">The University of Bridgeport, (Bridgeport, CT)         </text>
<text top="338" left="702" width="84" height="21" font="4">In progress </text>
<text top="359" left="108" width="273" height="20" font="4">MS in Biomedical/Electrical Engineering</text>
<text top="359" left="648" width="152" height="20" font="5"><i>(3.95 cumulative GPA)</i></text>
<text top="394" left="216" width="91" height="20" font="4">                   </text>
<text top="394" left="540" width="267" height="20" font="4">           (Expected Graduation May 2014)</text>
<text top="429" left="108" width="412" height="21" font="4">The California University of Pennsylvania, (California, PA)</text>
<text top="430" left="521" width="4" height="20" font="6"> </text>
<text top="429" left="540" width="269" height="21" font="4">                                                June 2012</text>
<text top="451" left="108" width="663" height="20" font="5"><i>B.S. in Pre­Medicine, Biology                                                                                     (3.59 cumulative </i></text>
<text top="470" left="108" width="202" height="20" font="5"><i>GPA)  </i>Dean’s List recognition</text>
<text top="505" left="108" width="701" height="21" font="4">The California University of Pennsylvania, (California, PA)                                                  June 2012</text>
<text top="527" left="108" width="158" height="20" font="5"><i>Gerontology Certificate</i></text>
<text top="527" left="486" width="313" height="20" font="5"><i>                                         (3.9 cumulative GPA)</i></text>
<text top="562" left="108" width="345" height="21" font="4">American Academy of CPR &amp; First Aid, (Online)</text>
<text top="562" left="486" width="25" height="20" font="4">      </text>
<text top="562" left="648" width="66" height="20" font="4">                </text>
<text top="562" left="714" width="95" height="21" font="4">October 2011</text>
<text top="583" left="108" width="124" height="20" font="5"><i>CPR Certification </i></text>
<text top="618" left="108" width="332" height="21" font="4">Moon Area High School, (Moon Township, PA) </text>
<text top="618" left="486" width="322" height="21" font="4">                                                             June 2008</text>
<text top="639" left="108" width="699" height="20" font="5"><i>Honors courses: Biology, Language Arts                                                                (3.63 cumulative GPA)   </i></text>
<text top="659" left="108" width="90" height="20" font="4">High Honors </text>
<text top="764" left="124" width="8" height="21" font="3">  </text>
<text top="765" left="108" width="15" height="20" font="3">➤</text>
<text top="764" left="132" width="171" height="21" font="3">WORK EXPERIENCE:</text>
<text top="800" left="108" width="315" height="21" font="2">Product Development Intern, (Pittsburgh PA)</text>
<text top="800" left="594" width="194" height="21" font="2">December 2013 to Current)</text>
<text top="837" left="108" width="142" height="20" font="2">ActivAided Orthotics</text>
<text top="871" left="135" width="8" height="22" font="7"></text>
<text top="873" left="162" width="543" height="19" font="8">Materials sourcing for an economically sustainable and durable product</text>
<text top="894" left="135" width="8" height="22" font="7"></text>
<text top="896" left="162" width="448" height="19" font="8">Improving the design for intuitiveness and user friendliness</text>
<text top="916" left="135" width="8" height="22" font="7"></text>
<text top="918" left="162" width="358" height="19" font="8">Navigating insurance reimbursement validation</text>
<text top="939" left="135" width="8" height="22" font="7"></text>
<text top="941" left="162" width="441" height="19" font="8">Simplifying and streamlining design for product fabrication</text>
<text top="961" left="135" width="8" height="22" font="7"></text>
<text top="963" left="162" width="400" height="19" font="8">Efficiency of order fulfillment and reaching end users</text>
<text top="984" left="135" width="8" height="22" font="7"></text>
<text top="986" left="162" width="299" height="19" font="8">Collecting feedback on product efficacy</text>
<text top="1006" left="135" width="8" height="22" font="7"></text>
<text top="1008" left="162" width="330" height="19" font="8">Log &amp; ship orders, invoicing, recordkeeping</text>
<text top="1029" left="135" width="8" height="22" font="7"></text>
<text top="1031" left="162" width="445" height="19" font="8">Administrative tasks – miscellaneous paperwork and tasks</text>
<text top="1051" left="135" width="8" height="22" font="7"></text>
<text top="1053" left="162" width="625" height="19" font="8">Inventory and supply chain - manage vendors, materials supply, finished inventory</text>
<text top="1117" left="803" width="8" height="17" font="9">1</text>
</page>
<page number="2" position="absolute" top="0" left="0" height="1188" width="918">
	<fontspec id="10" size="14" family="Times" color="#676767"/>
	<fontspec id="11" size="14" family="Symbol" color="#4d4d4d"/>
<text top="54" left="310" width="299" height="47" font="0">Raghen N. Morrow</text>
<text top="117" left="188" width="274" height="20" font="10">315 Shady Drive ⎮ Crescent, PA 15046 ⎮</text>
<text top="117" left="461" width="5" height="19" font="2"> </text>
<text top="117" left="467" width="264" height="20" font="10">(412) 874­9758 ⎮ raghenm@gmail.com</text>
<text top="137" left="135" width="8" height="22" font="7"></text>
<text top="139" left="162" width="554" height="19" font="8">Customer service - Provide first level of support to customers/distributors</text>
<text top="159" left="135" width="8" height="22" font="7"></text>
<text top="161" left="162" width="613" height="19" font="8">Company improvement - identify ways to help push ActivAided towards success!</text>
<text top="236" left="108" width="247" height="21" font="4">Assistant Manager, (South Port CT)</text>
<text top="236" left="540" width="239" height="21" font="4">          September 2013 to Jan 2014</text>
<text top="273" left="108" width="87" height="20" font="4">Tabouli Grill</text>
<text top="308" left="135" width="8" height="21" font="11"></text>
<text top="309" left="162" width="275" height="20" font="4">Counting inventory and ordering supplies</text>
<text top="344" left="135" width="8" height="21" font="11"></text>
<text top="346" left="162" width="248" height="20" font="4">Manage front of the house employees</text>
<text top="381" left="135" width="8" height="21" font="11"></text>
<text top="382" left="162" width="212" height="20" font="4">Ensure guest satisfaction is high</text>
<text top="417" left="135" width="8" height="21" font="11"></text>
<text top="419" left="162" width="335" height="20" font="4">Devising the front of the house employee schedule</text>
<text top="454" left="135" width="8" height="21" font="11"></text>
<text top="455" left="162" width="483" height="20" font="4"> Seat and assist guests. Proactively answer questions or relay information</text>
<text top="600" left="108" width="697" height="21" font="4">Graduate Assistantship, (Bridgeport CT)                                                 January 2013 to January 2014</text>
<text top="637" left="108" width="163" height="20" font="4">University of Bridgeport</text>
<text top="671" left="135" width="8" height="21" font="11"></text>
<text top="673" left="162" width="303" height="20" font="4">Organize and assist in biological lab activities</text>
<text top="708" left="135" width="8" height="21" font="11"></text>
<text top="709" left="162" width="335" height="20" font="4">Obtain sponsors the donate to the University funds</text>
<text top="744" left="135" width="8" height="21" font="11"></text>
<text top="746" left="162" width="248" height="20" font="4">Plan and organize the honors banquet</text>
<text top="818" left="108" width="697" height="21" font="4">Community Assistant, (Bridgeport CT)                                                January 2013 to September 2013</text>
<text top="854" left="108" width="145" height="20" font="4">Bridgeport University</text>
<text top="889" left="189" width="8" height="21" font="11"></text>
<text top="890" left="216" width="273" height="20" font="4">Assist residents with check in’s and out’s</text>
<text top="925" left="189" width="8" height="21" font="11"></text>
<text top="927" left="216" width="478" height="20" font="4">Administrative duties (answer phone, complete/ organize residents files)</text>
<text top="962" left="189" width="8" height="21" font="11"></text>
<text top="963" left="216" width="307" height="20" font="4">Monitor building for health and safety hazards</text>
<text top="1033" left="108" width="694" height="21" font="4">Floor Manager, Server &amp; Hostess, (Robinson, PA)                                           2007 to September 2013</text>
<text top="1117" left="803" width="8" height="17" font="9">2</text>
</page>
<page number="3" position="absolute" top="0" left="0" height="1188" width="918">
<text top="54" left="310" width="299" height="47" font="0">Raghen N. Morrow</text>
<text top="118" left="108" width="122" height="20" font="1">315 Shady Dirve</text>
<text top="118" left="230" width="13" height="20" font="2">⎮ </text>
<text top="118" left="243" width="142" height="20" font="1">Crescent, PA 15046</text>
<text top="118" left="385" width="278" height="20" font="2">⎮ (412) 874­9758 ⎮ raghenm@gmail.com</text>
<text top="138" left="108" width="152" height="20" font="4">Houlihan’s Restaurant </text>
<text top="173" left="162" width="598" height="20" font="4">• Manage front­of­house employees and effectively solve guest problems efficiently and   </text>
<text top="193" left="216" width="79" height="20" font="4">  effectively</text>
<text top="228" left="162" width="601" height="20" font="4">• Manage multiple tables while serving; requires a high­level of focus while under pressure</text>
<text top="263" left="162" width="489" height="20" font="4">• Seat and assist guests. Proactively answer questions or relay information</text>
<text top="334" left="108" width="688" height="21" font="4">Assistant Manager, (Robinson, PA)                                                            April 2012 to January 2013 </text>
<text top="356" left="108" width="146" height="20" font="4">Abercrombie &amp; Fitch </text>
<text top="391" left="162" width="211" height="20" font="4">• Shipment/ floor replenishment</text>
<text top="425" left="162" width="215" height="20" font="4">• Floor management/supervision</text>
<text top="460" left="162" width="339" height="20" font="4">• Visual manager (Directing and running floor sets)</text>
<text top="495" left="162" width="202" height="20" font="4">• Recruiting/hiring employees </text>
<text top="530" left="108" width="693" height="21" font="4">Personal Care Assistant, (McKees Rocks, PA)                                                             2011 to May 2012</text>
<text top="567" left="108" width="213" height="20" font="4">The Willows, Alzheimer’s Unit </text>
<text top="602" left="162" width="447" height="20" font="4">• Assist patients with daily living activities (i.e. bathing, eating, etc)</text>
<text top="636" left="162" width="558" height="20" font="4">• Liaison between families and patients; inform families of current status or progress</text>
<text top="671" left="162" width="624" height="20" font="4">• Direct and administer activities with patients to assist with memory loss and fine motor skills</text>
<text top="776" left="124" width="4" height="21" font="3"> </text>
<text top="777" left="108" width="15" height="20" font="3">➤</text>
<text top="776" left="128" width="254" height="21" font="3">LEADERSHIP AND ACTIVITIES:</text>
<text top="812" left="162" width="588" height="20" font="4">• Member of the Tri Beta Biology Honors Society, California University of Pennsylvania</text>
<text top="847" left="162" width="578" height="20" font="4">• Member of The National Society of Leadership and Success, California University of </text>
<text top="882" left="162" width="198" height="20" font="4">  Pennsylvania (2010­Present)</text>
<text top="917" left="162" width="633" height="20" font="4">• First Place Winner in the cellular/molecular biology research category, Commonwealth of       </text>
<text top="937" left="162" width="320" height="20" font="4">Pennsylvania University Biologists (April 2012)</text>
<text top="972" left="162" width="626" height="20" font="4">• Athletic scholarship recipient for women’s soccer, The California University of Pennsylvania</text>
<text top="1007" left="162" width="514" height="20" font="4">• Presidential Scholar, California University of Pennsylvania (2011 and 2012)</text>
<text top="1042" left="162" width="223" height="20" font="4">• Dementia training, The Willows</text>
<text top="1117" left="803" width="8" height="17" font="9">3</text>
</page>
<page number="4" position="absolute" top="0" left="0" height="1188" width="918">
<text top="54" left="310" width="299" height="47" font="0">Raghen N. Morrow</text>
<text top="117" left="188" width="274" height="20" font="10">315 Shady Drive ⎮ Crescent, PA 15046 ⎮</text>
<text top="117" left="461" width="5" height="19" font="2"> </text>
<text top="117" left="467" width="264" height="20" font="10">(412) 874­9758 ⎮ raghenm@gmail.com</text>
<text top="137" left="162" width="336" height="20" font="4">• Completed 550 hours of work in a 17­person unit</text>
<text top="172" left="135" width="8" height="21" font="11"></text>
<text top="173" left="162" width="476" height="20" font="4">President of University of Bridgeport Society of Women in Engineering</text>
<text top="208" left="135" width="8" height="21" font="11"></text>
<text top="210" left="162" width="528" height="20" font="4">University of Bridgeport Women in Engineering scholarship winner (Fall 2013)</text>
<text top="314" left="124" width="4" height="21" font="3"> </text>
<text top="315" left="108" width="15" height="20" font="3">➤</text>
<text top="314" left="128" width="116" height="21" font="3">REFERENCES:</text>
<text top="352" left="162" width="10" height="20" font="4">• </text>
<text top="351" left="172" width="301" height="21" font="4">Paula B. Caffrey, Ph.D., Assistant Professor</text>
<text top="388" left="162" width="8" height="20" font="4">  </text>
<text top="422" left="216" width="261" height="20" font="4">Biological and Environmental Sciences</text>
<text top="457" left="216" width="250" height="20" font="4">California University of Pennsylvania</text>
<text top="492" left="216" width="180" height="20" font="4">California, PA 15419­1394</text>
<text top="527" left="216" width="134" height="20" font="4">(724) 938­4209 (W)</text>
<text top="597" left="162" width="10" height="20" font="4">• </text>
<text top="597" left="172" width="192" height="21" font="4">Jan Biro, Assistant Manager</text>
<text top="668" left="216" width="148" height="20" font="4">Houlihan’s Restaurant</text>
<text top="703" left="216" width="182" height="20" font="4">100 Robinson Center Drive</text>
<text top="738" left="216" width="143" height="20" font="4">Pittsburgh, PA 15205</text>
<text top="773" left="216" width="129" height="20" font="4">(412) 508­9974 (C)</text>
<text top="843" left="162" width="10" height="20" font="4">• </text>
<text top="843" left="172" width="220" height="21" font="4">Sara Wiefling, Registered Nurse</text>
<text top="879" left="162" width="8" height="20" font="4">  </text>
<text top="914" left="216" width="93" height="20" font="4">Robinson, PA</text>
<text top="949" left="216" width="129" height="20" font="4">(412) 370­9766 (C)</text>
<text top="984" left="216" width="149" height="20" font="4">Swiefling@gmail.com</text>
<text top="1117" left="803" width="8" height="17" font="9">4</text>
</page>
<page number="5" position="absolute" top="0" left="0" height="1188" width="918">
<text top="54" left="310" width="299" height="47" font="0">Raghen N. Morrow</text>
<text top="118" left="108" width="122" height="20" font="1">315 Shady Dirve</text>
<text top="118" left="230" width="13" height="20" font="2">⎮ </text>
<text top="118" left="243" width="142" height="20" font="1">Crescent, PA 15046</text>
<text top="118" left="385" width="278" height="20" font="2">⎮ (412) 874­9758 ⎮ raghenm@gmail.com</text>
<text top="139" left="162" width="10" height="20" font="4">• </text>
<text top="138" left="172" width="264" height="21" font="4">Sara Meiss, Ph.D., Associate Professor</text>
<text top="175" left="162" width="8" height="20" font="4">  </text>
<text top="210" left="216" width="360" height="20" font="4">Department of Biological and Environmental Sciences</text>
<text top="245" left="216" width="250" height="20" font="4">California University of Pennsylvania</text>
<text top="280" left="216" width="141" height="20" font="4">California, PA 15419</text>
<text top="314" left="216" width="134" height="20" font="4">(724) 938­4203 (W)</text>
<text top="349" left="216" width="125" height="20" font="4">(412) 992­1491(C)</text>
<text top="1117" left="803" width="8" height="17" font="9">5</text>
</page>
</pdf2xml>
