<?xml version="1.0" encoding="UTF-8"?>
<!DOCTYPE pdf2xml SYSTEM "pdf2xml.dtd">

<pdf2xml producer="poppler" version="0.24.5">
<page number="1" position="absolute" top="0" left="0" height="1188" width="918">
	<fontspec id="0" size="19" family="Times" color="#000000"/>
	<fontspec id="1" size="12" family="Times" color="#000000"/>
	<fontspec id="2" size="12" family="Times" color="#000000"/>
<text top="108" left="378" width="161" height="25" font="0"><b>Teresa DeMore </b></text>
<text top="138" left="341" width="239" height="17" font="1">74 Sunset Rd, Arlington MA 02474 </text>
<text top="159" left="296" width="329" height="17" font="1">(781)-643-1923 (home), (617)-279-3184 (mobile) </text>
<text top="179" left="366" width="191" height="17" font="1">teresa.demore@gmail.com </text>
<text top="199" left="108" width="84" height="17" font="2"><b>EDUCATION</b></text>
<text top="199" left="192" width="15" height="20" font="1">​</text>
<text top="199" left="192" width="8" height="17" font="1">: </text>
<text top="219" left="108" width="204" height="17" font="2"><b>University of Maine, Orono </b></text>
<text top="240" left="108" width="242" height="17" font="1">Anticipated Graduation: May 2016 </text>
<text top="260" left="108" width="474" height="17" font="1">B.S. Animal and Veterinary Sciences; Animal Science Concentration </text>
<text top="280" left="108" width="311" height="17" font="1">Minor: Ecology and Environmental Sciences </text>
<text top="301" left="108" width="4" height="16" font="1"> </text>
<text top="321" left="108" width="86" height="17" font="2"><b>EXPERIENCE</b></text>
<text top="320" left="194" width="15" height="20" font="1">​</text>
<text top="321" left="194" width="8" height="16" font="1">: </text>
<text top="341" left="108" width="582" height="17" font="1">Zoo New England: Franklin Park Zoo, Boston, Massachusetts, May 2015 to July 2015 </text>
<text top="361" left="108" width="198" height="17" font="1">Animal Management Intern </text>
<text top="382" left="135" width="15" height="15" font="1">●</text>
<text top="381" left="162" width="150" height="17" font="1">Assisted Zoo Keepers </text>
<text top="402" left="135" width="15" height="15" font="1">●</text>
<text top="402" left="162" width="468" height="17" font="1">Spoke frequently to public through educational animal encounters </text>
<text top="422" left="135" width="15" height="15" font="1">●</text>
<text top="422" left="162" width="241" height="17" font="1">Frequently in charge of Zoo Teens </text>
<text top="442" left="108" width="4" height="17" font="1"> </text>
<text top="462" left="108" width="678" height="17" font="1">Cape Animal Referral and Emergency (CARE), Cape Cod, Massachusetts, May 2014 to August 2014 </text>
<text top="483" left="108" width="48" height="17" font="1">Intern </text>
<text top="503" left="135" width="15" height="15" font="1">●</text>
<text top="503" left="162" width="193" height="17" font="1">Assisted Physical Therapist </text>
<text top="523" left="108" width="4" height="17" font="1"> </text>
<text top="543" left="108" width="299" height="17" font="1">Dog Walker, October 2013 to January 2014 </text>
<text top="564" left="162" width="4" height="17" font="1"> </text>
<text top="584" left="108" width="382" height="17" font="1">Ledgebrook Animal Kennel, Woburn, Massachusetts  </text>
<text top="604" left="108" width="319" height="17" font="1">Kennel Attendant, April 2012 to January 2014 </text>
<text top="625" left="135" width="15" height="15" font="1">●</text>
<text top="624" left="162" width="390" height="17" font="1">Dogs, cats, and geese for overnight stay and/or day care </text>
<text top="645" left="135" width="15" height="15" font="1">●</text>
<text top="645" left="162" width="220" height="17" font="1">Trained multiple employees   </text>
<text top="665" left="135" width="15" height="15" font="1">●</text>
<text top="665" left="162" width="209" height="17" font="1">Handled medications/feeding </text>
<text top="685" left="108" width="4" height="16" font="1"> </text>
<text top="705" left="108" width="265" height="17" font="2"><b>VOLUNTEER/LEADERSHIP EXPERIENCE</b></text>
<text top="705" left="373" width="15" height="20" font="1">​</text>
<text top="705" left="373" width="7" height="17" font="1">: </text>
<text top="726" left="108" width="255" height="17" font="1">Peer Leader, April 2012 to May 2012 </text>
<text top="746" left="135" width="15" height="15" font="1">●</text>
<text top="746" left="162" width="196" height="17" font="1">Alcohol Awareness Speaker </text>
<text top="766" left="108" width="4" height="17" font="1"> </text>
<text top="786" left="108" width="259" height="17" font="1">Volunteer, January 2012-March 2012 </text>
<text top="807" left="135" width="15" height="15" font="1">●</text>
<text top="807" left="162" width="195" height="17" font="1">Ledgebrook Animal Kennel </text>
<text top="827" left="108" width="4" height="17" font="1"> </text>
<text top="847" left="108" width="229" height="17" font="1">Volunteer, April 2012-April 2012 </text>
<text top="868" left="135" width="15" height="15" font="1">●</text>
<text top="867" left="162" width="323" height="17" font="1">Heartworm clinic at Woburn Animal Hospital </text>
<text top="888" left="108" width="4" height="17" font="1"> </text>
<text top="908" left="108" width="477" height="17" font="1">Counselor, September 2008-February 2012 (Fall and Spring seasons) </text>
<text top="929" left="135" width="15" height="15" font="1">●</text>
<text top="928" left="162" width="207" height="17" font="1">Arlington Girls Lacrosse Club </text>
<text top="949" left="135" width="15" height="15" font="1">●</text>
<text top="948" left="162" width="350" height="17" font="1">Taught fundamentals of lacrosse to girls ages 8-14 </text>
<text top="969" left="108" width="4" height="17" font="2"><b> </b></text>
<text top="989" left="108" width="88" height="17" font="2"><b>Associations</b></text>
<text top="989" left="196" width="15" height="20" font="1">​</text>
<text top="989" left="196" width="10" height="17" font="2"><b>: </b></text>
<text top="1009" left="108" width="467" height="17" font="1">University of Maine Women's Lacrosse Club, September 2013-2014 </text>
</page>
</pdf2xml>
